CHANGES.txt
LICENSE.txt
MANIFEST.in
README.txt
bootstrap.py
setup.py
src/j01/__init__.py
src/j01.validate.egg-info/PKG-INFO
src/j01.validate.egg-info/SOURCES.txt
src/j01.validate.egg-info/dependency_links.txt
src/j01.validate.egg-info/namespace_packages.txt
src/j01.validate.egg-info/not-zip-safe
src/j01.validate.egg-info/requires.txt
src/j01.validate.egg-info/top_level.txt
src/j01/validate/README.txt
src/j01/validate/__init__.py
src/j01/validate/browser.py
src/j01/validate/configure.zcml
src/j01/validate/interfaces.py
src/j01/validate/jsonrpc.py
src/j01/validate/jsonrpc.zcml
src/j01/validate/widget.py
src/j01/validate/widget.zcml
src/j01/validate/css/j01.validate.css
src/j01/validate/js/j01.validate.js
src/j01/validate/tests/__init__.py
src/j01/validate/tests/checker.txt
src/j01/validate/tests/tests.py