Metadata-Version: 1.1
Name: j01.validate
Version: 0.5.2
Summary: JQuery beasd validation framework for z3c.form based widget
Home-page: http://pypi.python.org/pypi/j01.validate
Author: Roger Ineichen
Author-email: dev@projekt01.ch
License: ZPL 2.1
Keywords: zope3 z3c j01 validate validation framework
Platform: UNKNOWN
Classifier: Development Status :: 4 - Beta
Classifier: Environment :: Web Environment
Classifier: Intended Audience :: Developers
Classifier: License :: OSI Approved :: Zope Public License
Classifier: Programming Language :: Python
Classifier: Natural Language :: English
Classifier: Operating System :: OS Independent
Classifier: Topic :: Internet :: WWW/HTTP
Classifier: Framework :: Zope3
